pyFMG/__init__.py
pyFMG/fortianalyzer.py
pyFMG/fortimgr.py
pyfmg-0.8.6.3.dist-info/LICENSE
pyfmg-0.8.6.3.dist-info/METADATA
pyfmg-0.8.6.3.dist-info/WHEEL
pyfmg-0.8.6.3.dist-info/top_level.txt
pyfmg-0.8.6.3.dist-info/RECORD
