Metadata-Version: 2.1
Name: pyfmg
Version: 0.8.6.3
Summary: Represents the base components of the Fortinet FortiManager JSON-RPC interface
Home-page: https://github.com/p4r4n0y1ng/pyfmg
Author: p4r4n0y1ng
Author-email: jhuber@fortinet.com
License: Apache 2.0
License-File: LICENSE
Requires-Dist: requests
